odoo/addons/base_action_manager_access/LICENSE
odoo/addons/base_action_manager_access/README.rst
odoo/addons/base_action_manager_access/__init__.py
odoo/addons/base_action_manager_access/__manifest__.py
odoo/addons/base_action_manager_access/images/screen.png
odoo/addons/base_action_manager_access/models/__init__.py
odoo/addons/base_action_manager_access/models/ir_actions.py
odoo/addons/base_action_manager_access/security/ir.model.access.csv
odoo/addons/base_action_manager_access/static/description/icon.png
odoo/addons/base_action_manager_access/static/description/index.html
odoo/addons/base_action_manager_access/tests/TEST_INSTRUCTINS.rst
odoo_addon_base_action_manager_access-18.0.1.0.0.1.dist-info/METADATA
odoo_addon_base_action_manager_access-18.0.1.0.0.1.dist-info/WHEEL
odoo_addon_base_action_manager_access-18.0.1.0.0.1.dist-info/top_level.txt
odoo_addon_base_action_manager_access-18.0.1.0.0.1.dist-info/RECORD
